ntt_observable_list/ObservableList.py
ntt_observable_list/__init__.py
tests/ObservableListTest.py
tests/__init__.py
ntt_observable_list-1.0.0.dist-info/LICENSE
ntt_observable_list-1.0.0.dist-info/METADATA
ntt_observable_list-1.0.0.dist-info/WHEEL
ntt_observable_list-1.0.0.dist-info/top_level.txt
ntt_observable_list-1.0.0.dist-info/RECORD
