Metadata-Version: 2.1
Name: ntt-observable-list
Version: 1.0.0
Summary: List with ntt signal mechanism
Home-page: https://github.com/threezinedine/ntt-observable-list
Author: threezinedine
Author-email: threezinedine@email.com
License: UNKNOWN
Project-URL: Source, https://github.com/threezinedine/ntt-observable-list
Project-URL: Tracker, https://github.com/threezinedine/ntt-observable-list/issues
Keywords: signal,observable
Platform: UNKNOWN
Classifier: Development Status :: 3 - Alpha
Classifier: Intended Audience :: Developers
Classifier: Programming Language :: Python :: 3
Classifier: Programming Language :: Python :: 3.6
Classifier: Programming Language :: Python :: 3.7
Classifier: Programming Language :: Python :: 3.8
Classifier: Programming Language :: Python :: 3.9
License-File: LICENSE
Requires-Dist: ntt-signal
